[
  {"board":"TQBR","created_at":"2026-03-11T00:00:00+00:00","currency":"RUB","id":"instrument-1","instrument_type":"equity","is_active":true,"lot_size":10,"name":"Sberbank","ticker":"SBER","updated_at":"2026-03-11T00:00:00+00:00"},
  {"board":"TQBR","created_at":"2026-03-11T00:00:00+00:00","currency":"RUB","id":"instrument-2","instrument_type":"equity","is_active":true,"lot_size":10,"name":"Gazprom","ticker":"GAZP","updated_at":"2026-03-11T00:00:00+00:00"},
  {"board":"TQBR","created_at":"2026-03-11T00:00:00+00:00","currency":"RUB","id":"instrument-3","instrument_type":"equity","is_active":true,"lot_size":10,"name":"Lukoil","ticker":"LKOH","updated_at":"2026-03-11T00:00:00+00:00"},
  {"board":"TQBR","created_at":"2026-03-11T00:00:00+00:00","currency":"RUB","id":"instrument-4","instrument_type":"equity","is_active":true,"lot_size":10,"name":"Yandex","ticker":"YDEX","updated_at":"2026-03-11T00:00:00+00:00"},
  {"board":"TQBR","created_at":"2026-03-11T00:00:00+00:00","currency":"RUB","id":"instrument-5","instrument_type":"equity","is_active":true,"lot_size":10,"name":"Rosneft","ticker":"ROSN","updated_at":"2026-03-11T00:00:00+00:00"},
  {"board":"TQBR","created_at":"2026-03-11T00:00:00+00:00","currency":"RUB","id":"instrument-6","instrument_type":"equity","is_active":true,"lot_size":10,"name":"Novatek","ticker":"NVTK","updated_at":"2026-03-11T00:00:00+00:00"},
  {"board":"TQBR","created_at":"2026-03-11T00:00:00+00:00","currency":"RUB","id":"instrument-7","instrument_type":"equity","is_active":true,"lot_size":10,"name":"Magnit","ticker":"MGNT","updated_at":"2026-03-11T00:00:00+00:00"},
  {"board":"TQBR","created_at":"2026-03-11T00:00:00+00:00","currency":"RUB","id":"instrument-8","instrument_type":"equity","is_active":true,"lot_size":10,"name":"Norilsk Nickel","ticker":"GMKN","updated_at":"2026-03-11T00:00:00+00:00"},
  {"board":"TQBR","created_at":"2026-03-11T00:00:00+00:00","currency":"RUB","id":"instrument-9","instrument_type":"equity","is_active":true,"lot_size":10,"name":"Tatneft","ticker":"TATN","updated_at":"2026-03-11T00:00:00+00:00"},
  {"board":"TQBR","created_at":"2026-03-11T00:00:00+00:00","currency":"RUB","id":"instrument-10","instrument_type":"equity","is_active":true,"lot_size":10,"name":"VTB","ticker":"VTBR","updated_at":"2026-03-11T00:00:00+00:00"},
  {"board":"TQBR","created_at":"2026-03-11T00:00:00+00:00","currency":"RUB","id":"instrument-11","instrument_type":"equity","is_active":true,"lot_size":10,"name":"Severstal","ticker":"CHMF","updated_at":"2026-03-11T00:00:00+00:00"},
  {"board":"TQBR","created_at":"2026-03-11T00:00:00+00:00","currency":"RUB","id":"instrument-12","instrument_type":"equity","is_active":true,"lot_size":10,"name":"T-Bank","ticker":"T","updated_at":"2026-03-11T00:00:00+00:00"}
]
